hipose/__init__.py
hipose/imu.py
hipose/metrics.py
hipose/rotations.py
hipose/utils.py
hipose-0.7.1.dist-info/LICENSE
hipose-0.7.1.dist-info/METADATA
hipose-0.7.1.dist-info/WHEEL
hipose-0.7.1.dist-info/top_level.txt
hipose-0.7.1.dist-info/RECORD
