Metadata-Version: 2.1
Name: hipose
Version: 0.7.1
Summary: Human whole-body pose estimation using MARG multi-sensor data.
Home-page: https://github.com/ManuelPalermo/HumanInertialPose
Author: ManuelPalermo
Author-email: macpalermo@gmail.com
License: MIT
Platform: UNKNOWN
Classifier: Programming Language :: Python :: 3.9
Classifier: License :: OSI Approved :: MIT License
Classifier: Operating System :: OS Independent
License-File: LICENSE
Requires-Dist: numpy
Requires-Dist: scipy
Requires-Dist: ahrs
Provides-Extra: all
Requires-Dist: pandas ; extra == 'all'
Requires-Dist: openpyxl ; extra == 'all'
Requires-Dist: matplotlib ; extra == 'all'
Requires-Dist: seaborn ; extra == 'all'
Requires-Dist: PyQt5 ; extra == 'all'
Requires-Dist: PyOpenGL ; extra == 'all'
Requires-Dist: pyqtgraph ; extra == 'all'
Requires-Dist: sphinx ; extra == 'all'
Requires-Dist: sphinx-rtd-theme ; extra == 'all'
Requires-Dist: sphinx-autoapi ; extra == 'all'
Requires-Dist: pytest ; extra == 'all'
Requires-Dist: pytest-flake8 ; extra == 'all'
Requires-Dist: pytest-cov ; extra == 'all'
Requires-Dist: pytest-clarity ; extra == 'all'
Requires-Dist: pytest-randomly ; extra == 'all'
Requires-Dist: pytest-pydocstyle ; extra == 'all'
Provides-Extra: doc
Requires-Dist: sphinx ; extra == 'doc'
Requires-Dist: sphinx-rtd-theme ; extra == 'doc'
Requires-Dist: sphinx-autoapi ; extra == 'doc'
Provides-Extra: parse
Requires-Dist: pandas ; extra == 'parse'
Requires-Dist: openpyxl ; extra == 'parse'
Provides-Extra: plot
Requires-Dist: matplotlib ; extra == 'plot'
Requires-Dist: seaborn ; extra == 'plot'
Provides-Extra: test
Requires-Dist: pytest ; extra == 'test'
Requires-Dist: pytest-flake8 ; extra == 'test'
Requires-Dist: pytest-cov ; extra == 'test'
Requires-Dist: pytest-clarity ; extra == 'test'
Requires-Dist: pytest-randomly ; extra == 'test'
Requires-Dist: pytest-pydocstyle ; extra == 'test'
Provides-Extra: vis3d
Requires-Dist: PyQt5 ; extra == 'vis3d'
Requires-Dist: PyOpenGL ; extra == 'vis3d'
Requires-Dist: pyqtgraph ; extra == 'vis3d'
